videoutil/__init__.py
videoutil/audio.py
videoutil/cli.py
videoutil/combine.py
videoutil/compress.py
videoutil/connect.py
videoutil/generate.py
videoutil/rename.py
videoutil/split.py
videoutil/version.py
videoutil-0.1.7.dist-info/METADATA
videoutil-0.1.7.dist-info/WHEEL
videoutil-0.1.7.dist-info/entry_points.txt
videoutil-0.1.7.dist-info/top_level.txt
videoutil-0.1.7.dist-info/RECORD
