Metadata-Version: 2.2
Name: videoutil
Version: 0.1.7
Summary: A utility for video file operations
Home-page: https://github.com/ethanyanjiali/videoutil
Author: Ethan Li
Author-email: liyanjia92@gmail.com
Classifier: Programming Language :: Python :: 3
Classifier: Programming Language :: Python :: 3.8
Classifier: Programming Language :: Python :: 3.9
Classifier: Programming Language :: Python :: 3.10
Classifier: Programming Language :: Python :: 3.11
Classifier: License :: OSI Approved :: MIT License
Classifier: Operating System :: OS Independent
Requires-Python: >=3.8
Requires-Dist: click>=8.0.0
